Metadata-Version: 2.1
Name: robotframework-openstf
Version: 1.1.4
Summary: robot framework client to control remote device farm using openstf farm api
Home-page: https://opensourcetestops.gitlab.io/robotframeworkopenstf/
Author: mahmoud eltohamy
Author-email: mahmoud.mohammed.elhady@gmail.com
License: MIT
Platform: UNKNOWN
